LICENSE
README.md
pyproject.toml
setup.cfg
setup.py
orbit/__init__.py
orbit/__main__.py
orbit/cli.py
orbit/config.py
orbit/environment.py
orbit/exceptions.py
orbit/extensions.py
orbit/find.py
orbit/generate.py
orbit/log.py
orbit/main.py
orbit/prompt.py
orbit/replay.py
orbit/repository.py
orbit/utils.py
orbit/vcs.py
orbit/version.py
orbit/zipfile.py
orbit_client.egg-info/PKG-INFO
orbit_client.egg-info/SOURCES.txt
orbit_client.egg-info/dependency_links.txt
orbit_client.egg-info/entry_points.txt
orbit_client.egg-info/not-zip-safe
orbit_client.egg-info/requires.txt
orbit_client.egg-info/top_level.txt