Metadata-Version: 2.1
Name: orbit-client
Version: 1.1.0
Summary: A command-line utility that creates projects from project templates.
Home-page: https://gitlab.ftech.ai/nlp/va/template/orbit
Author: haonv
License: Apache License 2.0
Keywords: orbitPython,projects,project templates,Jinja2,skeleton,scaffolding,project directory,package,packaging
Requires-Python: >=3.7
License-File: LICENSE
